idea_distiller/__init__.py
idea_distiller/main.py
idea_distiller/prompts.py
idea_distiller-2025.12.21102518.dist-info/METADATA
idea_distiller-2025.12.21102518.dist-info/WHEEL
idea_distiller-2025.12.21102518.dist-info/top_level.txt
idea_distiller-2025.12.21102518.dist-info/RECORD
