Metadata-Version: 2.4
Name: idea-distiller
Version: 2025.12.21102518
Summary: A new package would process text inputs describing unconventional or controversial business or social initiatives, such as the 2012 program where homeless individuals were employed as mobile Wi-Fi hot
Author-email: idea-distiller <hi@eugene.plus>
License: MIT
Project-URL: Homepage, https://github.com/chigwell/idea-distiller
Requires-Python: >=3.9
Requires-Dist: langchain-llm7>=0.0.0
Requires-Dist: llmatch-messages>=0.0.0
Requires-Dist: langchain-core>=0.3.0
